examples/__init__.py
examples/fft/__init__.py
examples/fft/fft.py
examples/fft/fft_test.py
examples/sat/__init__.py
examples/sat/sat_tensornetwork.py
examples/sat/sat_tensornetwork_test.py
tensornetwork/__init__.py
tensornetwork/backend_contextmanager.py
tensornetwork/component_factory.py
tensornetwork/config.py
tensornetwork/ncon_interface.py
tensornetwork/network_components.py
tensornetwork/network_operations.py
tensornetwork/ops.py
tensornetwork/tensor.py
tensornetwork/utils.py
tensornetwork/version.py
tensornetwork/backends/__init__.py
tensornetwork/backends/abstract_backend.py
tensornetwork/backends/backend_factory.py
tensornetwork/backends/backend_test.py
tensornetwork/backends/decorators.py
tensornetwork/backends/decorators_test.py
tensornetwork/backends/jax/__init__.py
tensornetwork/backends/jax/jax_backend.py
tensornetwork/backends/jax/jax_backend_test.py
tensornetwork/backends/jax/jitted_functions.py
tensornetwork/backends/jax/jitted_functions_test.py
tensornetwork/backends/numpy/__init__.py
tensornetwork/backends/numpy/decompositions.py
tensornetwork/backends/numpy/decompositions_test.py
tensornetwork/backends/numpy/numpy_backend.py
tensornetwork/backends/numpy/numpy_backend_test.py
tensornetwork/backends/pytorch/__init__.py
tensornetwork/backends/pytorch/decompositions.py
tensornetwork/backends/pytorch/decompositions_test.py
tensornetwork/backends/pytorch/pytorch_backend.py
tensornetwork/backends/pytorch/pytorch_backend_test.py
tensornetwork/backends/pytorch/pytorch_tensornetwork_test.py
tensornetwork/backends/symmetric/__init__.py
tensornetwork/backends/symmetric/decompositions.py
tensornetwork/backends/symmetric/decompositions_test.py
tensornetwork/backends/symmetric/symmetric_backend.py
tensornetwork/backends/symmetric/symmetric_backend_test.py
tensornetwork/backends/tensorflow/__init__.py
tensornetwork/backends/tensorflow/decompositions.py
tensornetwork/backends/tensorflow/decompositions_test.py
tensornetwork/backends/tensorflow/tensordot2.py
tensornetwork-0.4.6.dist-info/AUTHORS
tensornetwork-0.4.6.dist-info/LICENSE
tensornetwork-0.4.6.dist-info/METADATA
tensornetwork-0.4.6.dist-info/WHEEL
tensornetwork-0.4.6.dist-info/top_level.txt
tensornetwork-0.4.6.dist-info/RECORD
