Metadata-Version: 2.1
Name: tensornetwork
Version: 0.4.6
Summary: A high level tensor network API for accelerated tensor network calculations.
Home-page: http://github.com/google/TensorNetwork
Author: The TensorNetwork Developers
Author-email: martin.ganahl@gmail.com
License: Apache 2.0
Platform: UNKNOWN
Requires-Python: >=3.7.0
